[{"title": "EEEE", "category": "zhi", "price": 9000, "description": "RRRRRR", "id": "1741463535"}, {"title": "\u043b\u043e\u043b", "category": "zhi", "price": 8000, "description": "\u043b\u043b\u043b\u0431", "id": "1741465365"}, {"title": "\u0440\u0440\u043e\u043e", "category": "zhi", "price": 9000, "description": "\u043b\u043b\u043b\u0434\u0434", "id": "1741465379"}, {"title": "\u0440\u0440\u0442", "category": "zhi", "price": 9999, "description": "\u043e\u043e\u043e\u043e\u043b", "id": "1741465398"}, {"title": "\u043e\u0442\u0440\u043e\u0434\u0436", "category": "zhi", "price": 999, "description": "\u043e\u043e\u043e\u043b\u043b\u0434", "id": "1741465421"}]